ansible_cry/__init__.py
ansible_cry/cli.py
ansible_cry-1.0.2.dist-info/entry_points.txt
ansible_cry-1.0.2.dist-info/LICENSE
ansible_cry-1.0.2.dist-info/WHEEL
ansible_cry-1.0.2.dist-info/METADATA
ansible_cry-1.0.2.dist-info/RECORD
