Metadata-Version: 2.1
Name: ansible-cry
Version: 1.0.2
Summary: Encrypt and decrypt ansible-vault string/file: Perfect for external tools.
Home-page: https://github.com/pylanglois/ansible-cry
License: MIT
Author: Pierre-Yves Langlois
Requires-Python: >=3.7,<4.0
Classifier: License :: OSI Approved :: MIT License
Classifier: Programming Language :: Python :: 3
Classifier: Programming Language :: Python :: 3.10
Classifier: Programming Language :: Python :: 3.7
Classifier: Programming Language :: Python :: 3.8
Classifier: Programming Language :: Python :: 3.9
Requires-Dist: ansible
Requires-Dist: plumbum
